plugantic/__init__.py
plugantic/_consts.py
plugantic/_helpers.py
plugantic/_types.py
plugantic/plugin.py
plugantic-0.2.1.dist-info/licenses/LICENSE
plugantic-0.2.1.dist-info/METADATA
plugantic-0.2.1.dist-info/WHEEL
plugantic-0.2.1.dist-info/top_level.txt
plugantic-0.2.1.dist-info/RECORD
