Metadata-Version: 2.4
Name: plugantic
Version: 0.2.1
Summary: Simplified extendable composition with pydantic
Author-email: Martin Kunze <martin@martinkunze.com>
Project-URL: Homepage, https://github.com/martinkunze/plugantic
Project-URL: Documentation, https://github.com/martinkunze/plugantic/blob/main/README.md
Project-URL: Source, https://github.com/martinkunze/plugantic
Requires-Python: >=3.8
License-File: LICENSE
Requires-Dist: pydantic
Requires-Dist: propert
Requires-Dist: typing-extensions
Dynamic: license-file
